codependpy/__init__.py
codependpy/ast_parser.py
codependpy/code_reconstructor.py
codependpy/dependency_bfs.py
codependpy/file_scanner.py
codependpy/index_builder.py
codependpy/main.py
codependpy/parse_args.py
codependpy/project_types.py
codependpy/utils.py
codependpy-0.1.1.dist-info/METADATA
codependpy-0.1.1.dist-info/WHEEL
codependpy-0.1.1.dist-info/entry_points.txt
codependpy-0.1.1.dist-info/top_level.txt
codependpy-0.1.1.dist-info/RECORD
