Metadata-Version: 2.1
Name: codependpy
Version: 0.1.1
Summary: A Python CLI tool for partial code extraction with dependency resolution.
Author-email: Your Name <your@email.com>
License: MIT
Keywords: ast,python,dependencies,partial-extraction,cli
Classifier: Programming Language :: Python :: 3
Classifier: License :: OSI Approved :: MIT License
Classifier: Operating System :: OS Independent
Requires-Python: >=3.7
